valueparser/__init__.py
valueparser/engine.py
valueparser/parsers.py
valueparser-0.1.5.dist-info/WHEEL
valueparser-0.1.5.dist-info/METADATA
valueparser-0.1.5.dist-info/RECORD
