Metadata-Version: 2.1
Name: valueparser
Version: 0.1.5
Summary: Python package for quick creation of tools to parse a value
Author: Sylvain Guieu
Author-email: sylvain.guieu@gmail.com
Requires-Python: >=3.7,<4.0
Classifier: Programming Language :: Python :: 3
Classifier: Programming Language :: Python :: 3.7
Classifier: Programming Language :: Python :: 3.8
Classifier: Programming Language :: Python :: 3.9
Classifier: Programming Language :: Python :: 3.10
Classifier: Programming Language :: Python :: 3.11
Requires-Dist: systemy (>=0.1.1,<0.2.0)
